[
    {
        "id": 1,
        "thumbnailUrl": "img/productos/ropa1.jpg",
        "brand": "marca",
        "title": "Titulo",
        "price": 20,
        "description": "descripcion",
        "size":"tamano"
        
    },
    {
        "id": 2,
        "thumbnailUrl": "img/productos/ropa1.jpg",
        "brand": "marca",
        "title": "Titulo",
        "price": 20,
        "description": "descripcion",
        "size":"tamano"
        
    },
    {
        "id": 3,
        "thumbnailUrl": "img/productos/ropa1.jpg",
        "brand": "marca",
        "title": "Titulo",
        "price": 20,
        "description": "descripcion",
        "size":"tamano"
        
    },
    {
        "id": 4,
        "thumbnailUrl": "img/productos/ropa1.jpg",
        "brand": "marca",
        "title": "Titulo",
        "price": 20,
        "description": "descripcion",
        "size":"tamano"
        
    },
    {
        "id": 5,
        "thumbnailUrl": "img/productos/ropa1.jpg",
        "brand": "marca",
        "title": "Titulo",
        "price": 20,
        "description": "descripcion",
        "size":"tamano"
        
    },
    {
        "id": 6,
        "thumbnailUrl": "img/productos/ropa1.jpg",
        "brand": "marca",
        "title": "Titulo",
        "price": 20,
        "description": "descripcion",
        "size":"tamano"
        
    },
    {
        "id": 7,
        "thumbnailUrl": "img/productos/ropa1.jpg",
        "brand": "marca",
        "title": "Titulo",
        "price": 20,
        "description": "descripcion",
        "size":"tamano"
        
    },
    {
        "id": 8,
        "thumbnailUrl": "img/productos/ropa1.jpg",
        "brand": "marca",
        "title": "Titulo",
        "price": 20,
        "description": "descripcion",
        "size":"tamano"
        
    }
    
    
    
]